{"Program":{"0":"1000-digit Fibonacci number","1":"10001st prime","2":"15 Days of Learning SQL","3":"1D Arrays in C","4":"3D Surface Area","5":"A Chessboard Game","6":"A Personalized Echo","7":"A Rule of Divisibility by 7","8":"A Very Big Sum","9":"A1","10":"ACBALL","11":"ACM ICPC Team","12":"ADACRA","13":"ADAKNG","14":"ADASCOOL","15":"ADASTAIR","16":"AGECAL","17":"ALEXNUMB","18":"ALEXTASK","19":"ALPHABET","20":"ALTARAY","21":"AMMEAT","22":"AMR15A","23":"AMSGAME1","24":"ANKTRAIN","25":"ANUARM","26":"ANUBTG","27":"ANUDTC","28":"ANUTHM","29":"ANUWTA","30":"APPROX","31":"AREAPERI","32":"ARRANGE","33":"ATM2","34":"ATTIC","35":"ATTND","36":"AVG","37":"Absolute Permutation","38":"Abstract Classes Polymorphism","39":"Accessing Inherited Functions","40":"African Cities","41":"Alien Username","42":"Almost Sorted","43":"Alphabet Rangoli","44":"Alternating Characters","45":"Alternative Matching","46":"Anagram","47":"Angry Professor","48":"Any or All","49":"Append and Delete","50":"Apple and Orange","51":"Arithmetic Operations","52":"Arithmetic Operators","53":"Array Manipulation","54":"Array Mathematics","55":"Array Reversal","56":"Arrays","57":"Arrays DS","58":"Arrays Introduction","59":"Asian Population","60":"Athlete Sort","61":"Attending Workshops","62":"Attribute Parser","63":"Average Population","64":"Average Population of Each Continent","65":"Awk 1","66":"Awk 2","67":"Awk 3","68":"Awk 4","69":"BANDMATR","70":"BFTT","71":"BINTREE","72":"BIT2A","73":"BITOBYT","74":"BRACKETS","75":"BRLADDER","76":"BROKPHON","77":"BSTOPS","78":"BUCKETS","79":"BUGCAL","80":"BUYING2","81":"BWCELL","82":"Backreferences To Failed Groups","83":"Ball Upwards","84":"Bash Basics - While Loop","85":"Bash Basics Check for File Existence","86":"Bash Basics Find Number of files in a Directory","87":"Basic Data Types","88":"Basic Probability Models and Rules","89":"Bayes rules Conditional probability Chain rule","90":"Bear and Steady Gene","91":"Beautiful Binary String","92":"Beautiful Days at the Movies","93":"Beautiful Triplets","94":"Between Two Sets","95":"Big Sorting","96":"Bigger is Greater","97":"Binary Tree Nodes","98":"Birthday Cake Candles","99":"Birthday Chocolate","100":"Bit Array","101":"Bitwise Operators","102":"Bon Appetit","103":"Bouncing Balls","104":"Box It","105":"Boxes through a Tunnel","106":"Branch Reset Groups","107":"Breaking the Records","108":"Build a Stack Exchange Scraper","109":"Building a Smart IDE Identifying comments","110":"Building a Smart IDEProgramming Language Detection","111":"C Program to print numbers from 1 to N without using semicolon","112":"C program to print without using a semicolon","113":"C00K0FF","114":"CAMPON","115":"CANDY123","116":"CAPPLE","117":"CARVANS","118":"CATFEED","119":"CATSDOGS","120":"CCOOK","121":"CEQUAL","122":"CFMM","123":"CFRTEST","124":"CHCHCL","125":"CHDOGS","126":"CHEFA","127":"CHEFAPAR","128":"CHEFARRP","129":"CHEFCBA","130":"CHEFDETE","131":"CHEFDIL","132":"CHEFFED","133":"CHEFGR","134":"CHEFING","135":"CHEFKEY","136":"CHEFPRMS","137":"CHEFROUT","138":"CHEFSETC","139":"CHEFSOCK","140":"CHEFSQ","141":"CHEFSTLT","142":"CHEFSTON","143":"CHEFSTUD","144":"CHEFSUM","145":"CHEFZOT","146":"CHFAR","147":"CHFCHK","148":"CHFIDEAL","149":"CHFINTRO","150":"CHFM","151":"CHFPARTY","152":"CHFTIRED","153":"CHN09","154":"CHN15A","155":"CHNGFUNC","156":"CHNGIT","157":"CHNGOR","158":"CHNUM","159":"CHOPRT","160":"CHRL2","161":"CHSERVE","162":"CHSQR","163":"CIELAB","164":"CIELDIST","165":"CIELRCPT","166":"CK87MEDI","167":"CK87QUER","168":"CLEANUP","169":"CLFIBD","170":"CLIPLX","171":"CMPRSS","172":"CNOTE","173":"CODERLIF","174":"COKE","175":"COLOR","176":"COMM3","177":"COMMUTE","178":"COMPILER","179":"CONFLIP","180":"COOMILK","181":"COPS","182":"COUPSYS","183":"CSUB","184":"CSUM","185":"CTHREE","186":"CV","187":"CVOTE","188":"Caesar Cipher","189":"Calculate the Nth term","190":"Calendar Module","191":"CamelCase","192":"Capitalize","193":"Capturing Non-Capturing Groups","194":"Cats and a Mouse","195":"Cavity Map","196":"Century From Year","197":"Challenges","198":"Check Strict Superset","199":"Check Subset","200":"Chocolate Feast","201":"Circular Array Rotation","202":"Class","203":"Class Find the Torsional Angle","204":"Class Template Specialization","205":"Class Templates","206":"Classes Dealing with Complex Numbers","207":"Classes and Objects","208":"Classic Hello World","209":"Climbing the Leaderboard","210":"Closest Numbers","211":"Collections OrderedDict","212":"Collections deque","213":"Collections namedtuple","214":"Common Child","215":"Common Denominators","216":"Company Logo","217":"Compare the Triplets","218":"Comparing Numbers","219":"Complementary DNA","220":"Compress the String","221":"Compute the Average","222":"Concatenate","223":"Concatenate an array with itself","224":"Conditional Statements","225":"Conditional Statements in C","226":"Contest Leaderboard","227":"Continuous Random Variables","228":"Convert month name to number","229":"Correctness and the Loop Invariant","230":"Count Strings","231":"Count the Digit","232":"Count the number of elements in an Array","233":"Counting Duplicates","234":"Counting Sort 1","235":"Counting Sort 2","236":"Counting Sundays","237":"Counting Valleys","238":"Cpp exception handling","239":"Cut 1","240":"Cut 2","241":"Cut 3","242":"Cut 4","243":"Cut 5","244":"Cut 6","245":"Cut 7","246":"Cut 8","247":"Cut 9","248":"Cut the sticks","249":"DAILY","250":"DANOW","251":"DECINC","252":"DECSTR","253":"DEPCHEF","254":"DEVARRAY","255":"DEVUGRAP","256":"DIET","257":"DIFFSUM","258":"DIRECTI","259":"DISCHAR","260":"DISTCODE","261":"DIVIDING","262":"DPAIRS","263":"DRAGNXOR","264":"DRGNBOOL","265":"DSTAPLS","266":"DWNLD","267":"Day 0 Data Types","268":"Day 0 Hello World","269":"Day 0 Hello World","270":"Day 0 Mean Median and Mode","271":"Day 0 Weighted Mean","272":"Day 1 Arithmetic Operators","273":"Day 1 Data Types","274":"Day 1 Functions","275":"Day 1 Interquartile Range","276":"Day 1 Let and Const","277":"Day 1 Quartiles","278":"Day 1 Standard Deviation","279":"Day 10 Binary Numbers","280":"Day 11 2D Arrays","281":"Day 12 Inheritance","282":"Day 13 Abstract Classes","283":"Day 14 Scope","284":"Day 15 Linked List","285":"Day 16 Exceptions String to Integer","286":"Day 17 More Exceptions","287":"Day 18 Queues and Stacks","288":"Day 19 Interfaces","289":"Day 2 Conditional Statements If Else","290":"Day 2 Conditional Statements Switch","291":"Day 2 Loops","292":"Day 2 Operators","293":"Day 20 Sorting","294":"Day 21 Generics","295":"Day 22 Binary Search Trees","296":"Day 23 BST Level Order Traversal","297":"Day 24 More Linked Lists","298":"Day 25 Running Time and Complexity","299":"Day 26 Nested Logic","300":"Day 27 Testing","301":"Day 28 RegEx Patterns and Intro to Databases","302":"Day 29 Bitwise AND","303":"Day 3 Arrays","304":"Day 3 Intro to Conditional Statements","305":"Day 3 Throw","306":"Day 3 Try Catch and Finally","307":"Day 4 Binomial Distribution I","308":"Day 4 Binomial Distribution II","309":"Day 4 Class vs Instance","310":"Day 4 Classes","311":"Day 4 Count Objects","312":"Day 4 Create a Rectangle Object","313":"Day 4 Geometric Distribution I","314":"Day 4 Geometric Distribution II","315":"Day 5 Arrow Functions","316":"Day 5 Inheritance","317":"Day 5 Loops","318":"Day 5 Normal Distribution I","319":"Day 5 Normal Distribution II","320":"Day 5 Poisson Distribution I","321":"Day 5 Poisson Distribution II","322":"Day 5 Template Literals","323":"Day 6 Bitwise Operators","324":"Day 6 JavaScript Dates","325":"Day 6 Lets Review","326":"Day 6 The Central Limit Theorem I","327":"Day 6 The Central Limit Theorem II","328":"Day 6 The Central Limit Theorem III","329":"Day 7 Arrays","330":"Day 7 Pearson Correlation Coefficient I","331":"Day 7 Regular Expressions I","332":"Day 7 Regular Expressions II","333":"Day 7 Regular Expressions III","334":"Day 7 Spearmans Rank Correlation Coefficient","335":"Day 8 Buttons Container","336":"Day 8 Create a Button","337":"Day 8 Dictionaries and Maps","338":"Day 8 Least Square Regression Line","339":"Day 9 Binary Calculator","340":"Day 9 Multiple Linear Regression","341":"Day 9 Recursion 3","342":"Day of the Programmer","343":"Decorators 2 Name Directory","344":"Default Arguments","345":"DefaultDict Tutorial","346":"Deque STL","347":"Designer Door Mat","348":"Designer PDF Viewer","349":"Detect Floating Point Number","350":"Detect HTML Attributes","351":"Detect HTML Tags","352":"Detect HTML Tags, Attributes and Attribute Values","353":"Detect HTML links","354":"Detect the Domain Name","355":"Detect the Email Addresses","356":"Detecting Valid Latitude and Longitude Pairs","357":"Diagonal Difference","358":"Digit Frequency","359":"Directions Reduction","360":"Discrete Random Variables","361":"Disemvowel Trolls","362":"Display an element of an array","363":"Divisible Sum Pairs","364":"Dot and Cross","365":"Draw The Triangle 1","366":"Draw The Triangle 2","367":"Drawing Book","368":"Drying Potatoes","369":"EASYPROB","370":"EATTWICE","371":"EGRANDR","372":"EID","373":"ELEVSTRS","374":"ENCMSG","375":"ENTEXAM","376":"EQUALITY","377":"ERROR","378":"EVENT","379":"EXAM1","380":"EXUNA","381":"Easy Diagonal","382":"Easy wallpaper","383":"Electronics Shop","384":"Emas Supercomputer","385":"Employee Names","386":"Employee Salaries","387":"Encryption","388":"Equalize the Array","389":"Even Fibonacci numbers","390":"Even or Odd","391":"Exceptional Server","392":"Exceptions","393":"Excluding Specific Characters","394":"Execute both if and else statements in C or Cpp simultaneously","395":"Expressions Matter","396":"Extra Long Factorials","397":"Eye and Identity","398":"FANCY","399":"FBMT","400":"FCTRL","401":"FCTRL2","402":"FLOW001","403":"FLOW002","404":"FLOW004","405":"FLOW005","406":"FLOW006","407":"FLOW007","408":"FLOW008","409":"FLOW009","410":"FLOW010","411":"FLOW011","412":"FLOW013","413":"FLOW014","414":"FLOW015","415":"FLOW016","416":"FLOW017","417":"FLOW018","418":"FRGTNLNG","419":"FRUITS","420":"FSQRT","421":"Factorial digit sum","422":"Fair Rations","423":"Filter an Array with Patterns","424":"Find A Sub-Word","425":"Find Angle MBC","426":"Find Digits","427":"Find HackerRank","428":"Find a Word","429":"Find a string","430":"Find the Median","431":"Find the Runner Up Score","432":"Finding the percentage","433":"Flatland Space Stations","434":"Floor Ceil and Rint","435":"Folding your way to the moon","436":"For Loop","437":"For Loop in C","438":"Forming a Magic Square","439":"Forward References","440":"Function 1 hello world","441":"Functions","442":"Functions and Fractals Recursive Trees Bash","443":"Functions in C","444":"Funny String","445":"GARDENSQ","446":"GCD2","447":"GDOG","448":"GIT01","449":"GOODBAD","450":"GOODSET","451":"GREG","452":"GRID","453":"Game of Stones","454":"Game of Thrones I","455":"Gemstones","456":"Getting started with conditionals","457":"Going to the cinema","458":"Grading Students","459":"Grasshopper - Messi goals function","460":"Grasshopper - Terminal game move function","461":"Grasshopper Check for factor","462":"Grep 1","463":"Grep 2","464":"Grep 3","465":"Grep A","466":"Grep B","467":"Group, Groups & Groupdict","468":"Growth of a Population","469":"H1","470":"HEADBOB","471":"HHAL","472":"HILLS","473":"HMAPPY2","474":"HORSES","475":"HOWMANY","476":"HP18","477":"HRDSEQ","478":"HS08TEST","479":"HTML Parser Part 1","480":"HTML Parser Part 2","481":"HUNGALGO","482":"HackerRank Language","483":"HackerRank Tweets","484":"HackerRank in a String","485":"Halloween Sale","486":"Happy Ladybugs","487":"Head of a Text File 1","488":"Head of a Text File 2","489":"Hello World in C","490":"Heros root","491":"Hex Color Code","492":"Higher Than 75 Marks","493":"Highest Value Palindrome","494":"Highly divisible triangular number","495":"Hotel Prices","496":"ICL1901","497":"ICL1902","498":"ICPC16A","499":"ICPC16B","500":"ICPC16C","501":"INTEST","502":"IP Address Validation","503":"Ice Cream Parlor","504":"Incorrect Regex","505":"Inheritance Introduction","506":"Inherited Code","507":"Inner and Outer","508":"Input","509":"Input and Output","510":"Insertion Sort Part 1","511":"Insertion Sort Part 2","512":"Integers Come In All Sizes","513":"Interviews","514":"Intro to Tutorial Challenges","515":"Introduction to Sets","516":"Is n divisible by x and y","517":"Iterables and Iterators","518":"J7","519":"JDELAY","520":"JOHNY","521":"Japan Population","522":"Japanese Cities Attributes","523":"Japanese Cities Names","524":"Jumping on the Clouds","525":"Jumping on the Clouds Revisited","526":"KCHESS","527":"KFIB","528":"KINGSHIP","529":"KNIGHTMV","530":"KOL15A","531":"KOL16B","532":"KOL16J","533":"KS2","534":"KTTABLE","535":"Kangaroo","536":"Keep Hydrated","537":"Keep up the hoop","538":"LADDU","539":"LAPIN","540":"LCH15JAB","541":"LCOLLIS","542":"LEBOMBS","543":"LEDIV","544":"LELEMON","545":"LEPERMUT","546":"LIFE","547":"LIFELTD","548":"LIKECS01","549":"LIKECS02","550":"LISDIGIT","551":"LONGSEQ","552":"LOSTMAX","553":"LTM40AB","554":"LUCKFOUR","555":"LUCKY5","556":"LUCKYSTR","557":"Large sum","558":"Largest palindrome product","559":"Largest prime factor","560":"Largest product in a grid","561":"Largest product in a series","562":"Larrys Array","563":"Lattice paths","564":"Learning Shell Count to 30","565":"Left Rotation","566":"LetsEcho","567":"Library Fine","568":"Linear Algebra","569":"Lisas Workbook","570":"List Comprehensions","571":"Lists","572":"Lonely Integer Bash","573":"Looking for a benefactor","574":"Looping and Skipping","575":"Looping with Numbers","576":"Loops","577":"Lower Bound STL","578":"MAANDI","579":"MAGICHF","580":"MAGICJAR","581":"MAKEART","582":"MARCHA1","583":"MATCHES","584":"MATPAN","585":"MAX2","586":"MAXDIFF","587":"MAXREM","588":"MDL","589":"MEDIC","590":"MGCSET","591":"MINPERM","592":"MISSP","593":"MNMX","594":"MOVIEWKN","595":"MRO","596":"MSNSADM1","597":"MUFFINS3","598":"MXCH","599":"MXMEDIAN","600":"Magic Spells","601":"Making Anagrams","602":"Manasa and Stones","603":"Map and Lambda Function","604":"Maps STL","605":"Marcs Cakewalk","606":"Mars Exploration","607":"Matching Anything But a Newline","608":"Matching Character Ranges","609":"Matching Digits Non-Digit Characters","610":"Matching Ending Items","611":"Matching One Or More Repetitions","612":"Matching Same Text Again Again","613":"Matching Specific Characters","614":"Matching Specific String","615":"Matching Start End","616":"Matching Whitespace Non-Whitespace Character","617":"Matching Word Boundaries","618":"Matching Word Non-Word Character","619":"Matching Zero Or More Repetitions","620":"Matching {x, y} Repetitions","621":"Matching {x} Repetitions","622":"Matrix Layer Rotation","623":"Matrix Script","624":"Maximize It","625":"Maximum Length Difference","626":"Maximum Perimeter Triangle","627":"Maximum and minimum of two numbers without using any loop or condition","628":"Mean Var and Std","629":"Merge the Tools","630":"Messages Order","631":"Middle of a Text File","632":"Migratory Birds","633":"Min and Max","634":"Mini-Max Sum","635":"Minimum Absolute Difference in an Array","636":"Minimum Distances","637":"Missing Numbers","638":"Mod Divmod","639":"Modified Kaprekar Numbers","640":"More on Conditionals","641":"Multi Level Inheritance","642":"Multiples of 3 and 5","643":"Mutations","644":"NDIFFPAL","645":"NITIKA","646":"NOCODING","647":"NOLOGIC","648":"NOMATCH","649":"NOTINCOM","650":"NUKES","651":"NUMGAME2","652":"NUMTOW","653":"NW1","654":"Names scores","655":"Negative Lookahead","656":"Negative Lookbehind","657":"Nested Lists","658":"New Companies","659":"No Idea","660":"Non Divisible Subset","661":"Number letter counts","662":"Number spiral diagonals","663":"OJUMPS","664":"OMWG","665":"ONOZ","666":"ONP","667":"ORACLCS","668":"ORDTEAMS","669":"Occupations","670":"Ollivanders Inventory","671":"Operator Overloading","672":"Opposite number","673":"Organizing Containers of Balls","674":"Overload Operators","675":"Overloading Ostream Operator","676":"PAIRING","677":"PAJAPONG","678":"PALL01","679":"PCJ18A","680":"PCJ18B","681":"PCJ18C","682":"PCYCLE","683":"PERFCONT","684":"PERMEXIS","685":"PERMUT2","686":"PLAYFIT","687":"PLAYPIAN","688":"PLAYSTR","689":"PLZLYKME","690":"POTATOES","691":"PPATTERN","692":"PPSUM","693":"PRB01","694":"PREFINVS","695":"PRGIFT","696":"PROB","697":"PROC18A","698":"PROSUM","699":"PROXYC","700":"PRPOTION","701":"PUPPYGM","702":"Palindrome Index","703":"Pangrams","704":"Parameter Passing in CPP","705":"Paste 1","706":"Paste 2","707":"Paste 3","708":"Paste 4","709":"Permutations of Strings","710":"Picking Numbers","711":"Piling Up","712":"Placements","713":"Playing With Character","714":"Plus Minus","715":"Pointer","716":"Pointers in C","717":"Polar Coordinates","718":"Polynomials","719":"Population Density Difference","720":"Positive Lookahead","721":"Positive Lookbehind","722":"Post Transition","723":"Power Mod Power","724":"Power digit sum","725":"Preprocessor Solution","726":"Primorial Of a Number","727":"Print Function","728":"Print Pretty","729":"Print Prime Numbers","730":"Printing Pattern using Loops","731":"Printing Tokens","732":"Python Division","733":"Python Evaluation","734":"Python If-Else","735":"QUADROOT","736":"QUALPREL","737":"Queens Attack II","738":"Querying the Document","739":"Quicksort 1 Partition","740":"RAINBOWA","741":"RD19","742":"REACTION","743":"RECIPE","744":"RECTANGL","745":"RECTSQ","746":"REDONE","747":"REMISS","748":"RESQ","749":"RIGHTRI","750":"RNDPAIR","751":"ROBOGAME","752":"RPD","753":"RRCOPY","754":"RRJOKE","755":"RRSTONE","756":"RRSUM","757":"Re findall & Re finditer","758":"Re split","759":"Re start Re end","760":"Read in an Array","761":"Rectangle Area","762":"Reduce Function","763":"Regex Password Validation","764":"Regex Substitution","765":"Remove First and Last Character","766":"Remove String Spaces","767":"Remove anchor from URL","768":"Remove the First Capital Letter from Each Element","769":"Repeated String","770":"Return a list of files filtered by file extension","771":"Return the latest modified file","772":"Reverser","773":"Revising Aggregations Averages","774":"Revising Aggregations The Count Function","775":"Revising Aggregations The Sum Function","776":"Revising the Select Query I","777":"Revising the Select Query II","778":"Running Time of Algorithms","779":"SC31","780":"SEALINE","781":"SEBIHWY","782":"SEGM01","783":"SFXPAL","784":"SIMDISH","785":"SIMPSTAT","786":"SMPAIR","787":"SMRSTR","788":"SNACKUP","789":"SNAKPROC","790":"SNCKYEAR","791":"SNELECT","792":"SPAMCLAS","793":"SPCANDY","794":"SPELLBOB","795":"SPLST","796":"SQL Project Planning","797":"START01","798":"STICKS","799":"STONES","800":"STRLBP","801":"STRPALIN","802":"SUBANAGR","803":"SUBGCD","804":"SUBINC","805":"SUBMIN","806":"SUMTRIAN","807":"SURVIVE","808":"Save the Prisoner","809":"Say Hello World With C++","810":"Say Hello World With Python","811":"Saying Hi","812":"Sed Command 1","813":"Sed Command 2","814":"Sed Command 3","815":"Sed Command 4","816":"Sed Command 5","817":"Select All","818":"Select By ID","819":"Separate the Numbers","820":"Sequence Equation","821":"Service Lane","822":"Set Mutations","823":"Set add","824":"Set difference","825":"Set discard remove pop","826":"Set intersection","827":"Set symmetric_difference","828":"Set union","829":"Sets STL","830":"Shape and Reshape","831":"Sherlock and Anagrams","832":"Sherlock and Array","833":"Sherlock and Squares","834":"Sherlock and the Valid String","835":"Show multiples of 2 numbers within a range","836":"Simple Array Sum","837":"Slice an Array","838":"Small Triangles Large Triangles","839":"Smallest multiple","840":"Sock Merchant","841":"Solve Me First","842":"Sort Command 1","843":"Sort Command 2","844":"Sort Command 3","845":"Sort Command 4","846":"Sort Command 5","847":"Sort Command 6","848":"Sort Command 7","849":"Sorting Array of Strings","850":"Sparse Arrays","851":"Special Pythagorean triplet","852":"Speed Control","853":"Split the Phone Numbers","854":"Staircase","855":"Standardize Mobile Number Using Decorators","856":"Strange Counter","857":"String Construction","858":"String Formatting","859":"String Split and Join","860":"String Validators","861":"String repeat","862":"StringStream","863":"Strings","864":"Strong Password","865":"Structs","866":"Structuring the Document","867":"Students Marks Sum","868":"Substituting Variables Into Strings Padded Numbers","869":"Sum and Difference of Two Numbers","870":"Sum and Prod","871":"Sum of Digits of a Five Digit Number","872":"Sum of angles","873":"Sum of odd numbers","874":"Sum square difference","875":"Summation of primes","876":"Super Reduced String","877":"Swap two variables in one line","878":"Symmetric Difference","879":"Symmetric Pairs","880":"TABLET","881":"TACHSTCK","882":"TALAZY","883":"TAVISUAL","884":"TEMPLELA","885":"TEST","886":"THREEDIF","887":"THREEFR","888":"TICKETS5","889":"TLG","890":"TOTR","891":"TRICKYDL","892":"TRICOIN","893":"TRISQ","894":"TRUEDARE","895":"TSORT","896":"TSTROBOT","897":"TTENIS","898":"TWEED","899":"TWONMS","900":"TWOSTR","901":"TWTCLOSE","902":"TYPING","903":"Tail of a Text File 1","904":"Tail of a Text File 2","905":"Target Date","906":"Taum and Bday","907":"Text Alignment","908":"Text Wrap","909":"The Blunder","910":"The Bomberman Game","911":"The British and American Style of Spelling","912":"The Captain's Room","913":"The Full Counting Sort","914":"The Hurdle Race","915":"The Love Letter Mystery","916":"The Minion Game","917":"The Report","918":"The Time in Words","919":"The World of Numbers","920":"Third Angle of a Triangle","921":"Time Conversion","922":"Time Delta","923":"Top Competitors","924":"Top Earners","925":"Tortoise racing","926":"Tower Breakers","927":"Tr Command 1","928":"Tr Command 2","929":"Tr Command 3","930":"Transpose and Flatten","931":"Triangle Quest","932":"Triangle Quest 2","933":"Tuples","934":"Twice as old","935":"Two Characters","936":"Two Strings","937":"Two to One","938":"Type of Triangle","939":"UCL","940":"UK and US Part 2","941":"UNICOURS","942":"URCALC","943":"UTMOPR","944":"Uniq Command 1","945":"Uniq Command 2","946":"Uniq Command 3","947":"Uniq Command 4","948":"Utopian Identification Number","949":"Utopian Tree","950":"VALIDSTK","951":"VCS","952":"VILTRIBE","953":"VOTERS","954":"VOWELTB","955":"Valid PAN format","956":"Validating Credit Card Numbers","957":"Validating Email Addresses With a Filter","958":"Validating Postal Codes","959":"Validating Roman Numerals","960":"Validating UID","961":"Validating and Parsing Email Addresses","962":"Validating phone numbers","963":"Variable Sized Arrays","964":"Variadic functions in C","965":"Variadics","966":"Vector Erase","967":"Vector Sort","968":"Viral Advertising","969":"Virtual Functions","970":"Volume of cuboid","971":"WALK","972":"WATSCORE","973":"WDTBAM","974":"Weather Observation Station 1","975":"Weather Observation Station 10","976":"Weather Observation Station 11","977":"Weather Observation Station 12","978":"Weather Observation Station 13","979":"Weather Observation Station 14","980":"Weather Observation Station 15","981":"Weather Observation Station 16","982":"Weather Observation Station 17","983":"Weather Observation Station 18","984":"Weather Observation Station 19","985":"Weather Observation Station 2","986":"Weather Observation Station 20","987":"Weather Observation Station 3","988":"Weather Observation Station 4","989":"Weather Observation Station 5","990":"Weather Observation Station 6","991":"Weather Observation Station 7","992":"Weather Observation Station 8","993":"Weather Observation Station 9","994":"Weighted Uniform Strings","995":"What time is it in Japan","996":"Whats Your Name","997":"Word Order","998":"Words Score","999":"Write a function","1000":"XENTASK","1001":"XML 1 Find the Score","1002":"XML2 Find the Maximum Depth","1003":"XORNEY","1004":"ZUBREACH","1005":"ZUBTRCNT","1006":"Zeros and Ones","1007":"Zipped","1008":"collections Counter","1009":"ginortS","1010":"itertools combinations","1011":"itertools combinations with replacement","1012":"itertools permutations","1013":"itertools product","1014":"sWAP cASE"},"Language":{"0":"py","1":"py","2":"sql","3":"c","4":"py","5":"py","6":"sh","7":"sh","8":"py","9":"py","10":"py","11":"py","12":"py","13":"py","14":"py","15":"py","16":"py","17":"py","18":"py","19":"py","20":"py","21":"py","22":"py","23":"py","24":"py","25":"py","26":"py","27":"py","28":"py","29":"py","30":"py","31":"py","32":"py","33":"py","34":"py","35":"py","36":"py","37":"py","38":"cpp","39":"cpp","40":"sql","41":"py","42":"py","43":"py","44":"py","45":"py","46":"py","47":"py","48":"py","49":"py","50":"py","51":"sh","52":"py","53":"py","54":"py","55":"c","56":"py","57":"py","58":"cpp","59":"sql","60":"py","61":"cpp","62":"cpp","63":"sql","64":"sql","65":"sh","66":"sh","67":"sh","68":"sh","69":"py","70":"py","71":"py","72":"py","73":"py","74":"py","75":"py","76":"py","77":"py","78":"py","79":"py","80":"py","81":"py","82":"py","83":"sh","84":"sh","85":"sh","86":"sh","87":"cpp","88":"py","89":"py","90":"py","91":"py","92":"py","93":"py","94":"py","95":"py","96":"py","97":"sql","98":"py","99":"py","100":"cpp","101":"c","102":"py","103":"sh","104":"cpp","105":"c","106":"php","107":"py","108":"py","109":"py","110":"py","111":"c","112":"c","113":"py","114":"py","115":"py","116":"py","117":"py","118":"py","119":"py","120":"py","121":"py","122":"py","123":"py","124":"py","125":"py","126":"py","127":"py","128":"py","129":"py","130":"py","131":"py","132":"py","133":"py","134":"py","135":"py","136":"py","137":"py","138":"py","139":"py","140":"py","141":"py","142":"py","143":"py","144":"py","145":"py","146":"py","147":"py","148":"py","149":"py","150":"py","151":"py","152":"py","153":"py","154":"py","155":"py","156":"py","157":"py","158":"py","159":"py","160":"py","161":"py","162":"py","163":"py","164":"py","165":"py","166":"py","167":"py","168":"py","169":"py","170":"py","171":"py","172":"py","173":"py","174":"py","175":"py","176":"py","177":"py","178":"py","179":"py","180":"py","181":"py","182":"py","183":"py","184":"py","185":"py","186":"py","187":"py","188":"py","189":"c","190":"py","191":"py","192":"py","193":"py","194":"py","195":"py","196":"sh","197":"sql","198":"py","199":"py","200":"py","201":"py","202":"cpp","203":"py","204":"cpp","205":"cpp","206":"py","207":"cpp","208":"sh","209":"py","210":"py","211":"py","212":"py","213":"py","214":"py","215":"sh","216":"py","217":"py","218":"sh","219":"sh","220":"py","221":"sh","222":"py","223":"sh","224":"cpp","225":"c","226":"sql","227":"py","228":"sh","229":"py","230":"py","231":"sh","232":"sh","233":"sh","234":"py","235":"py","236":"py","237":"py","238":"cpp","239":"sh","240":"sh","241":"sh","242":"sh","243":"sh","244":"sh","245":"sh","246":"sh","247":"sh","248":"py","249":"py","250":"py","251":"py","252":"py","253":"py","254":"py","255":"py","256":"py","257":"py","258":"py","259":"py","260":"py","261":"py","262":"py","263":"py","264":"py","265":"py","266":"py","267":"js","268":"js","269":"py","270":"py","271":"py","272":"js","273":"py","274":"js","275":"py","276":"js","277":"py","278":"py","279":"py","280":"py","281":"py","282":"py","283":"py","284":"py","285":"py","286":"py","287":"py","288":"py","289":"js","290":"js","291":"js","292":"py","293":"py","294":"cpp","295":"py","296":"py","297":"py","298":"py","299":"py","300":"py","301":"py","302":"py","303":"js","304":"py","305":"js","306":"js","307":"py","308":"py","309":"py","310":"js","311":"js","312":"js","313":"py","314":"py","315":"js","316":"js","317":"py","318":"py","319":"py","320":"py","321":"py","322":"js","323":"js","324":"js","325":"py","326":"py","327":"py","328":"py","329":"py","330":"py","331":"js","332":"js","333":"js","334":"py","335":"js","336":"js","337":"py","338":"py","339":"js","340":"py","341":"py","342":"py","343":"py","344":"py","345":"py","346":"cpp","347":"py","348":"py","349":"py","350":"py","351":"py","352":"py","353":"py","354":"py","355":"py","356":"py","357":"py","358":"c","359":"sh","360":"py","361":"sh","362":"sh","363":"py","364":"py","365":"sql","366":"sql","367":"py","368":"sh","369":"py","370":"py","371":"py","372":"py","373":"py","374":"py","375":"py","376":"py","377":"py","378":"py","379":"py","380":"py","381":"sh","382":"sh","383":"py","384":"py","385":"sql","386":"sql","387":"py","388":"py","389":"py","390":"sh","391":"cpp","392":"py","393":"py","394":"c","395":"sh","396":"py","397":"py","398":"py","399":"py","400":"py","401":"py","402":"py","403":"py","404":"py","405":"py","406":"py","407":"py","408":"py","409":"py","410":"py","411":"py","412":"py","413":"py","414":"py","415":"py","416":"py","417":"py","418":"py","419":"py","420":"py","421":"py","422":"py","423":"sh","424":"py","425":"py","426":"py","427":"py","428":"py","429":"py","430":"py","431":"py","432":"py","433":"py","434":"py","435":"sh","436":"cpp","437":"c","438":"py","439":"php","440":"sh","441":"cpp","442":"sh","443":"c","444":"py","445":"py","446":"py","447":"py","448":"py","449":"py","450":"py","451":"py","452":"py","453":"py","454":"py","455":"py","456":"sh","457":"sh","458":"py","459":"sh","460":"sh","461":"sh","462":"sh","463":"sh","464":"sh","465":"sh","466":"sh","467":"py","468":"sh","469":"py","470":"py","471":"py","472":"py","473":"py","474":"py","475":"py","476":"py","477":"py","478":"py","479":"py","480":"py","481":"py","482":"py","483":"py","484":"py","485":"py","486":"py","487":"sh","488":"sh","489":"c","490":"sh","491":"py","492":"sql","493":"py","494":"py","495":"cpp","496":"py","497":"py","498":"py","499":"py","500":"py","501":"py","502":"py","503":"py","504":"py","505":"cpp","506":"cpp","507":"py","508":"py","509":"cpp","510":"py","511":"py","512":"py","513":"sql","514":"py","515":"py","516":"sh","517":"py","518":"py","519":"py","520":"py","521":"sql","522":"sql","523":"sql","524":"py","525":"py","526":"py","527":"py","528":"py","529":"py","530":"py","531":"py","532":"py","533":"py","534":"py","535":"py","536":"sh","537":"sh","538":"py","539":"py","540":"py","541":"py","542":"py","543":"py","544":"py","545":"py","546":"py","547":"py","548":"py","549":"py","550":"py","551":"py","552":"py","553":"py","554":"py","555":"py","556":"py","557":"py","558":"py","559":"py","560":"py","561":"py","562":"py","563":"py","564":"sh","565":"py","566":"sh","567":"py","568":"py","569":"py","570":"py","571":"py","572":"sh","573":"sh","574":"sh","575":"sh","576":"py","577":"cpp","578":"py","579":"py","580":"py","581":"py","582":"py","583":"py","584":"py","585":"py","586":"py","587":"py","588":"py","589":"py","590":"py","591":"py","592":"py","593":"py","594":"py","595":"py","596":"py","597":"py","598":"py","599":"py","600":"cpp","601":"py","602":"py","603":"py","604":"cpp","605":"py","606":"py","607":"py","608":"py","609":"py","610":"py","611":"py","612":"py","613":"py","614":"py","615":"py","616":"py","617":"py","618":"py","619":"py","620":"py","621":"py","622":"py","623":"py","624":"py","625":"sh","626":"py","627":"c","628":"py","629":"py","630":"cpp","631":"sh","632":"py","633":"py","634":"py","635":"py","636":"py","637":"py","638":"py","639":"py","640":"sh","641":"cpp","642":"py","643":"py","644":"py","645":"py","646":"py","647":"py","648":"py","649":"py","650":"py","651":"py","652":"py","653":"py","654":"py","655":"py","656":"py","657":"py","658":"sql","659":"py","660":"py","661":"py","662":"py","663":"py","664":"py","665":"py","666":"py","667":"py","668":"py","669":"sql","670":"sql","671":"cpp","672":"sh","673":"py","674":"cpp","675":"cpp","676":"py","677":"py","678":"py","679":"py","680":"py","681":"py","682":"py","683":"py","684":"py","685":"py","686":"py","687":"py","688":"py","689":"py","690":"py","691":"py","692":"py","693":"py","694":"py","695":"py","696":"py","697":"py","698":"py","699":"py","700":"py","701":"py","702":"py","703":"py","704":"cpp","705":"sh","706":"sh","707":"sh","708":"sh","709":"c","710":"py","711":"py","712":"sql","713":"c","714":"py","715":"cpp","716":"c","717":"py","718":"py","719":"sql","720":"py","721":"py","722":"c","723":"py","724":"py","725":"cpp","726":"sh","727":"py","728":"cpp","729":"sql","730":"c","731":"c","732":"py","733":"py","734":"py","735":"py","736":"py","737":"py","738":"c","739":"py","740":"py","741":"py","742":"py","743":"py","744":"py","745":"py","746":"py","747":"py","748":"py","749":"py","750":"py","751":"py","752":"py","753":"py","754":"py","755":"py","756":"py","757":"py","758":"py","759":"py","760":"sh","761":"cpp","762":"py","763":"sh","764":"py","765":"sh","766":"sh","767":"sh","768":"sh","769":"py","770":"sh","771":"sh","772":"sh","773":"sql","774":"sql","775":"sql","776":"sql","777":"sql","778":"py","779":"py","780":"py","781":"py","782":"py","783":"py","784":"py","785":"py","786":"py","787":"py","788":"py","789":"py","790":"py","791":"py","792":"py","793":"py","794":"py","795":"py","796":"sql","797":"py","798":"py","799":"py","800":"py","801":"py","802":"py","803":"py","804":"py","805":"py","806":"py","807":"py","808":"py","809":"cpp","810":"py","811":"py","812":"sh","813":"sh","814":"sh","815":"sh","816":"sh","817":"sql","818":"sql","819":"py","820":"py","821":"py","822":"py","823":"py","824":"py","825":"py","826":"py","827":"py","828":"py","829":"cpp","830":"py","831":"py","832":"py","833":"py","834":"py","835":"sh","836":"py","837":"sh","838":"c","839":"py","840":"py","841":"py","842":"sh","843":"sh","844":"sh","845":"sh","846":"sh","847":"sh","848":"sh","849":"c","850":"py","851":"py","852":"sh","853":"py","854":"py","855":"py","856":"py","857":"py","858":"py","859":"py","860":"py","861":"sh","862":"cpp","863":"cpp","864":"py","865":"cpp","866":"c","867":"c","868":"sh","869":"c","870":"py","871":"c","872":"sh","873":"sh","874":"py","875":"py","876":"py","877":"cpp","878":"py","879":"sql","880":"py","881":"py","882":"py","883":"py","884":"py","885":"py","886":"py","887":"py","888":"py","889":"py","890":"py","891":"py","892":"py","893":"py","894":"py","895":"py","896":"py","897":"py","898":"py","899":"py","900":"py","901":"py","902":"py","903":"sh","904":"sh","905":"sh","906":"py","907":"py","908":"py","909":"sql","910":"py","911":"py","912":"py","913":"py","914":"py","915":"py","916":"py","917":"sql","918":"py","919":"sh","920":"sh","921":"py","922":"py","923":"sql","924":"sql","925":"sh","926":"py","927":"sh","928":"sh","929":"sh","930":"py","931":"py","932":"py","933":"py","934":"sh","935":"py","936":"py","937":"sh","938":"sql","939":"py","940":"py","941":"py","942":"py","943":"py","944":"sh","945":"sh","946":"sh","947":"sh","948":"py","949":"py","950":"py","951":"py","952":"py","953":"py","954":"py","955":"py","956":"py","957":"py","958":"py","959":"py","960":"py","961":"py","962":"py","963":"cpp","964":"c","965":"cpp","966":"cpp","967":"cpp","968":"py","969":"cpp","970":"sh","971":"py","972":"py","973":"py","974":"sql","975":"sql","976":"sql","977":"sql","978":"sql","979":"sql","980":"sql","981":"sql","982":"sql","983":"sql","984":"sql","985":"sql","986":"sql","987":"sql","988":"sql","989":"sql","990":"sql","991":"sql","992":"sql","993":"sql","994":"py","995":"sh","996":"py","997":"py","998":"py","999":"py","1000":"py","1001":"py","1002":"py","1003":"py","1004":"py","1005":"py","1006":"py","1007":"py","1008":"py","1009":"py","1010":"py","1011":"py","1012":"py","1013":"py","1014":"py"},"Category":{"0":"ProjectEuler","1":"ProjectEuler","2":"HackerRank-SQL","3":"HackerRank-C","4":"HackerRank-ProblemSolving","5":"HackerRank-ProblemSolving","6":"HackerRank-LinuxShell","7":"CodeWars-Shell","8":"HackerRank-ProblemSolving","9":"CodeChef","10":"CodeChef","11":"HackerRank-ProblemSolving","12":"CodeChef","13":"CodeChef","14":"CodeChef","15":"CodeChef","16":"CodeChef","17":"CodeChef","18":"CodeChef","19":"CodeChef","20":"CodeChef","21":"CodeChef","22":"CodeChef","23":"CodeChef","24":"CodeChef","25":"CodeChef","26":"CodeChef","27":"CodeChef","28":"CodeChef","29":"CodeChef","30":"CodeChef","31":"CodeChef","32":"CodeChef","33":"CodeChef","34":"CodeChef","35":"CodeChef","36":"CodeChef","37":"HackerRank-ProblemSolving","38":"HackerRank-C++","39":"HackerRank-C++","40":"HackerRank-SQL","41":"HackerRank-Regex","42":"HackerRank-ProblemSolving","43":"HackerRank-Python","44":"HackerRank-ProblemSolving","45":"HackerRank-Regex","46":"HackerRank-ProblemSolving","47":"HackerRank-ProblemSolving","48":"HackerRank-Python","49":"HackerRank-ProblemSolving","50":"HackerRank-ProblemSolving","51":"HackerRank-LinuxShell","52":"HackerRank-Python","53":"HackerRank-ProblemSolving","54":"HackerRank-Python","55":"HackerRank-C","56":"HackerRank-Python","57":"HackerRank-ProblemSolving","58":"HackerRank-C++","59":"HackerRank-SQL","60":"HackerRank-Python","61":"HackerRank-C++","62":"HackerRank-C++","63":"HackerRank-SQL","64":"HackerRank-SQL","65":"HackerRank-LinuxShell","66":"HackerRank-LinuxShell","67":"HackerRank-LinuxShell","68":"HackerRank-LinuxShell","69":"CodeChef","70":"CodeChef","71":"CodeChef","72":"CodeChef","73":"CodeChef","74":"CodeChef","75":"CodeChef","76":"CodeChef","77":"CodeChef","78":"CodeChef","79":"CodeChef","80":"CodeChef","81":"CodeChef","82":"HackerRank-Regex","83":"CodeWars-Shell","84":"CodeWars-Shell","85":"CodeWars-Shell","86":"CodeWars-Shell","87":"HackerRank-C++","88":"HackerEarth-MachineLearning","89":"HackerEarth-MachineLearning","90":"HackerRank-ProblemSolving","91":"HackerRank-ProblemSolving","92":"HackerRank-ProblemSolving","93":"HackerRank-ProblemSolving","94":"HackerRank-ProblemSolving","95":"HackerRank-ProblemSolving","96":"HackerRank-ProblemSolving","97":"HackerRank-SQL","98":"HackerRank-ProblemSolving","99":"HackerRank-ProblemSolving","100":"HackerRank-C++","101":"HackerRank-C","102":"HackerRank-ProblemSolving","103":"CodeWars-Shell","104":"HackerRank-C++","105":"HackerRank-C","106":"HackerRank-Regex","107":"HackerRank-ProblemSolving","108":"HackerRank-Regex","109":"HackerRank-Regex","110":"HackerRank-Regex","111":"Featured","112":"Featured","113":"CodeChef","114":"CodeChef","115":"CodeChef","116":"CodeChef","117":"CodeChef","118":"CodeChef","119":"CodeChef","120":"CodeChef","121":"CodeChef","122":"CodeChef","123":"CodeChef","124":"CodeChef","125":"CodeChef","126":"CodeChef","127":"CodeChef","128":"CodeChef","129":"CodeChef","130":"CodeChef","131":"CodeChef","132":"CodeChef","133":"CodeChef","134":"CodeChef","135":"CodeChef","136":"CodeChef","137":"CodeChef","138":"CodeChef","139":"CodeChef","140":"CodeChef","141":"CodeChef","142":"CodeChef","143":"CodeChef","144":"CodeChef","145":"CodeChef","146":"CodeChef","147":"CodeChef","148":"CodeChef","149":"CodeChef","150":"CodeChef","151":"CodeChef","152":"CodeChef","153":"CodeChef","154":"CodeChef","155":"CodeChef","156":"CodeChef","157":"CodeChef","158":"CodeChef","159":"CodeChef","160":"CodeChef","161":"CodeChef","162":"CodeChef","163":"CodeChef","164":"CodeChef","165":"CodeChef","166":"CodeChef","167":"CodeChef","168":"CodeChef","169":"CodeChef","170":"CodeChef","171":"CodeChef","172":"CodeChef","173":"CodeChef","174":"CodeChef","175":"CodeChef","176":"CodeChef","177":"CodeChef","178":"CodeChef","179":"CodeChef","180":"CodeChef","181":"CodeChef","182":"CodeChef","183":"CodeChef","184":"CodeChef","185":"CodeChef","186":"CodeChef","187":"CodeChef","188":"HackerRank-ProblemSolving","189":"HackerRank-C","190":"HackerRank-Python","191":"HackerRank-ProblemSolving","192":"HackerRank-Python","193":"HackerRank-Regex","194":"HackerRank-ProblemSolving","195":"HackerRank-ProblemSolving","196":"CodeWars-Shell","197":"HackerRank-SQL","198":"HackerRank-Python","199":"HackerRank-Python","200":"HackerRank-ProblemSolving","201":"HackerRank-ProblemSolving","202":"HackerRank-C++","203":"HackerRank-Python","204":"HackerRank-C++","205":"HackerRank-C++","206":"HackerRank-Python","207":"HackerRank-C++","208":"CodeWars-Shell","209":"HackerRank-ProblemSolving","210":"HackerRank-ProblemSolving","211":"HackerRank-Python","212":"HackerRank-Python","213":"HackerRank-Python","214":"HackerRank-ProblemSolving","215":"CodeWars-Shell","216":"HackerRank-Python","217":"HackerRank-ProblemSolving","218":"HackerRank-LinuxShell","219":"CodeWars-Shell","220":"HackerRank-Python","221":"HackerRank-LinuxShell","222":"HackerRank-Python","223":"HackerRank-LinuxShell","224":"HackerRank-C++","225":"HackerRank-C","226":"HackerRank-SQL","227":"HackerEarth-MachineLearning","228":"CodeWars-Shell","229":"HackerRank-ProblemSolving","230":"HackerRank-ProblemSolving","231":"CodeWars-Shell","232":"HackerRank-LinuxShell","233":"CodeWars-Shell","234":"HackerRank-ProblemSolving","235":"HackerRank-ProblemSolving","236":"ProjectEuler","237":"HackerRank-ProblemSolving","238":"HackerRank-C++","239":"HackerRank-LinuxShell","240":"HackerRank-LinuxShell","241":"HackerRank-LinuxShell","242":"HackerRank-LinuxShell","243":"HackerRank-LinuxShell","244":"HackerRank-LinuxShell","245":"HackerRank-LinuxShell","246":"HackerRank-LinuxShell","247":"HackerRank-LinuxShell","248":"HackerRank-ProblemSolving","249":"CodeChef","250":"CodeChef","251":"CodeChef","252":"CodeChef","253":"CodeChef","254":"CodeChef","255":"CodeChef","256":"CodeChef","257":"CodeChef","258":"CodeChef","259":"CodeChef","260":"CodeChef","261":"CodeChef","262":"CodeChef","263":"CodeChef","264":"CodeChef","265":"CodeChef","266":"CodeChef","267":"HackerRank-JS","268":"HackerRank-JS","269":"HackerRank-Code","270":"HackerRank-Statistics","271":"HackerRank-Statistics","272":"HackerRank-JS","273":"HackerRank-Code","274":"HackerRank-JS","275":"HackerRank-Statistics","276":"HackerRank-JS","277":"HackerRank-Statistics","278":"HackerRank-Statistics","279":"HackerRank-Code","280":"HackerRank-Code","281":"HackerRank-Code","282":"HackerRank-Code","283":"HackerRank-Code","284":"HackerRank-Code","285":"HackerRank-Code","286":"HackerRank-Code","287":"HackerRank-Code","288":"HackerRank-Code","289":"HackerRank-JS","290":"HackerRank-JS","291":"HackerRank-JS","292":"HackerRank-Code","293":"HackerRank-Code","294":"HackerRank-Code","295":"HackerRank-Code","296":"HackerRank-Code","297":"HackerRank-Code","298":"HackerRank-Code","299":"HackerRank-Code","300":"HackerRank-Code","301":"HackerRank-Code","302":"HackerRank-Code","303":"HackerRank-JS","304":"HackerRank-Code","305":"HackerRank-JS","306":"HackerRank-JS","307":"HackerRank-Statistics","308":"HackerRank-Statistics","309":"HackerRank-Code","310":"HackerRank-JS","311":"HackerRank-JS","312":"HackerRank-JS","313":"HackerRank-Statistics","314":"HackerRank-Statistics","315":"HackerRank-JS","316":"HackerRank-JS","317":"HackerRank-Code","318":"HackerRank-Statistics","319":"HackerRank-Statistics","320":"HackerRank-Statistics","321":"HackerRank-Statistics","322":"HackerRank-JS","323":"HackerRank-JS","324":"HackerRank-JS","325":"HackerRank-Code","326":"HackerRank-Statistics","327":"HackerRank-Statistics","328":"HackerRank-Statistics","329":"HackerRank-Code","330":"HackerRank-Statistics","331":"HackerRank-JS","332":"HackerRank-JS","333":"HackerRank-JS","334":"HackerRank-Statistics","335":"HackerRank-JS","336":"HackerRank-JS","337":"HackerRank-Code","338":"HackerRank-Statistics","339":"HackerRank-JS","340":"HackerRank-Statistics","341":"HackerRank-Code","342":"HackerRank-ProblemSolving","343":"HackerRank-Python","344":"HackerRank-Python","345":"HackerRank-Python","346":"HackerRank-C++","347":"HackerRank-Python","348":"HackerRank-ProblemSolving","349":"HackerRank-Python","350":"HackerRank-Regex","351":"HackerRank-Regex","352":"HackerRank-Python","353":"HackerRank-Regex","354":"HackerRank-Regex","355":"HackerRank-Regex","356":"HackerRank-Regex","357":"HackerRank-ProblemSolving","358":"HackerRank-C","359":"CodeWars-Shell","360":"HackerEarth-MachineLearning","361":"CodeWars-Shell","362":"HackerRank-LinuxShell","363":"HackerRank-ProblemSolving","364":"HackerRank-Python","365":"HackerRank-SQL","366":"HackerRank-SQL","367":"HackerRank-ProblemSolving","368":"CodeWars-Shell","369":"CodeChef","370":"CodeChef","371":"CodeChef","372":"CodeChef","373":"CodeChef","374":"CodeChef","375":"CodeChef","376":"CodeChef","377":"CodeChef","378":"CodeChef","379":"CodeChef","380":"CodeChef","381":"CodeWars-Shell","382":"CodeWars-Shell","383":"HackerRank-ProblemSolving","384":"HackerRank-ProblemSolving","385":"HackerRank-SQL","386":"HackerRank-SQL","387":"HackerRank-ProblemSolving","388":"HackerRank-ProblemSolving","389":"ProjectEuler","390":"CodeWars-Shell","391":"HackerRank-C++","392":"HackerRank-Python","393":"HackerRank-Regex","394":"Featured","395":"CodeWars-Shell","396":"HackerRank-ProblemSolving","397":"HackerRank-Python","398":"CodeChef","399":"CodeChef","400":"CodeChef","401":"CodeChef","402":"CodeChef","403":"CodeChef","404":"CodeChef","405":"CodeChef","406":"CodeChef","407":"CodeChef","408":"CodeChef","409":"CodeChef","410":"CodeChef","411":"CodeChef","412":"CodeChef","413":"CodeChef","414":"CodeChef","415":"CodeChef","416":"CodeChef","417":"CodeChef","418":"CodeChef","419":"CodeChef","420":"CodeChef","421":"ProjectEuler","422":"HackerRank-ProblemSolving","423":"HackerRank-LinuxShell","424":"HackerRank-Regex","425":"HackerRank-Python","426":"HackerRank-ProblemSolving","427":"HackerRank-Regex","428":"HackerRank-Regex","429":"HackerRank-Python","430":"HackerRank-ProblemSolving","431":"HackerRank-Python","432":"HackerRank-Python","433":"HackerRank-ProblemSolving","434":"HackerRank-Python","435":"CodeWars-Shell","436":"HackerRank-C++","437":"HackerRank-C","438":"HackerRank-ProblemSolving","439":"HackerRank-Regex","440":"CodeWars-Shell","441":"HackerRank-C++","442":"HackerRank-LinuxShell","443":"HackerRank-C","444":"HackerRank-ProblemSolving","445":"CodeChef","446":"CodeChef","447":"CodeChef","448":"CodeChef","449":"CodeChef","450":"CodeChef","451":"CodeChef","452":"CodeChef","453":"HackerRank-ProblemSolving","454":"HackerRank-ProblemSolving","455":"HackerRank-ProblemSolving","456":"HackerRank-LinuxShell","457":"CodeWars-Shell","458":"HackerRank-ProblemSolving","459":"CodeWars-Shell","460":"CodeWars-Shell","461":"CodeWars-Shell","462":"HackerRank-LinuxShell","463":"HackerRank-LinuxShell","464":"HackerRank-LinuxShell","465":"HackerRank-LinuxShell","466":"HackerRank-LinuxShell","467":"HackerRank-Python","468":"CodeWars-Shell","469":"CodeChef","470":"CodeChef","471":"CodeChef","472":"CodeChef","473":"CodeChef","474":"CodeChef","475":"CodeChef","476":"CodeChef","477":"CodeChef","478":"CodeChef","479":"HackerRank-Python","480":"HackerRank-Python","481":"CodeChef","482":"HackerRank-Regex","483":"HackerRank-Regex","484":"HackerRank-ProblemSolving","485":"HackerRank-ProblemSolving","486":"HackerRank-ProblemSolving","487":"HackerRank-LinuxShell","488":"HackerRank-LinuxShell","489":"HackerRank-C","490":"CodeWars-Shell","491":"HackerRank-Python","492":"HackerRank-SQL","493":"HackerRank-ProblemSolving","494":"ProjectEuler","495":"HackerRank-C++","496":"CodeChef","497":"CodeChef","498":"CodeChef","499":"CodeChef","500":"CodeChef","501":"CodeChef","502":"HackerRank-Regex","503":"HackerRank-ProblemSolving","504":"HackerRank-Python","505":"HackerRank-C++","506":"HackerRank-C++","507":"HackerRank-Python","508":"HackerRank-Python","509":"HackerRank-C++","510":"HackerRank-ProblemSolving","511":"HackerRank-ProblemSolving","512":"HackerRank-Python","513":"HackerRank-SQL","514":"HackerRank-ProblemSolving","515":"HackerRank-Python","516":"CodeWars-Shell","517":"HackerRank-Python","518":"CodeChef","519":"CodeChef","520":"CodeChef","521":"HackerRank-SQL","522":"HackerRank-SQL","523":"HackerRank-SQL","524":"HackerRank-ProblemSolving","525":"HackerRank-ProblemSolving","526":"CodeChef","527":"CodeChef","528":"CodeChef","529":"CodeChef","530":"CodeChef","531":"CodeChef","532":"CodeChef","533":"CodeChef","534":"CodeChef","535":"HackerRank-ProblemSolving","536":"CodeWars-Shell","537":"CodeWars-Shell","538":"CodeChef","539":"CodeChef","540":"CodeChef","541":"CodeChef","542":"CodeChef","543":"CodeChef","544":"CodeChef","545":"CodeChef","546":"CodeChef","547":"CodeChef","548":"CodeChef","549":"CodeChef","550":"CodeChef","551":"CodeChef","552":"CodeChef","553":"CodeChef","554":"CodeChef","555":"CodeChef","556":"CodeChef","557":"ProjectEuler","558":"ProjectEuler","559":"ProjectEuler","560":"ProjectEuler","561":"ProjectEuler","562":"HackerRank-ProblemSolving","563":"ProjectEuler","564":"CodeWars-Shell","565":"HackerRank-ProblemSolving","566":"HackerRank-LinuxShell","567":"HackerRank-ProblemSolving","568":"HackerRank-Python","569":"HackerRank-ProblemSolving","570":"HackerRank-Python","571":"HackerRank-Python","572":"HackerRank-LinuxShell","573":"CodeWars-Shell","574":"HackerRank-LinuxShell","575":"HackerRank-LinuxShell","576":"HackerRank-Python","577":"HackerRank-C++","578":"CodeChef","579":"CodeChef","580":"CodeChef","581":"CodeChef","582":"CodeChef","583":"CodeChef","584":"CodeChef","585":"CodeChef","586":"CodeChef","587":"CodeChef","588":"CodeChef","589":"CodeChef","590":"CodeChef","591":"CodeChef","592":"CodeChef","593":"CodeChef","594":"CodeChef","595":"CodeChef","596":"CodeChef","597":"CodeChef","598":"CodeChef","599":"CodeChef","600":"HackerRank-C++","601":"HackerRank-ProblemSolving","602":"HackerRank-ProblemSolving","603":"HackerRank-Python","604":"HackerRank-C++","605":"HackerRank-ProblemSolving","606":"HackerRank-ProblemSolving","607":"HackerRank-Regex","608":"HackerRank-Regex","609":"HackerRank-Regex","610":"HackerRank-Regex","611":"HackerRank-Regex","612":"HackerRank-Regex","613":"HackerRank-Regex","614":"HackerRank-Regex","615":"HackerRank-Regex","616":"HackerRank-Regex","617":"HackerRank-Regex","618":"HackerRank-Regex","619":"HackerRank-Regex","620":"HackerRank-Regex","621":"HackerRank-Regex","622":"HackerRank-ProblemSolving","623":"HackerRank-Python","624":"HackerRank-Python","625":"CodeWars-Shell","626":"HackerRank-ProblemSolving","627":"Featured","628":"HackerRank-Python","629":"HackerRank-Python","630":"HackerRank-C++","631":"HackerRank-LinuxShell","632":"HackerRank-ProblemSolving","633":"HackerRank-Python","634":"HackerRank-ProblemSolving","635":"HackerRank-ProblemSolving","636":"HackerRank-ProblemSolving","637":"HackerRank-ProblemSolving","638":"HackerRank-Python","639":"HackerRank-ProblemSolving","640":"HackerRank-LinuxShell","641":"HackerRank-C++","642":"ProjectEuler","643":"HackerRank-Python","644":"CodeChef","645":"CodeChef","646":"CodeChef","647":"CodeChef","648":"CodeChef","649":"CodeChef","650":"CodeChef","651":"CodeChef","652":"CodeChef","653":"CodeChef","654":"ProjectEuler","655":"HackerRank-Regex","656":"HackerRank-Regex","657":"HackerRank-Python","658":"HackerRank-SQL","659":"HackerRank-Python","660":"HackerRank-ProblemSolving","661":"ProjectEuler","662":"ProjectEuler","663":"CodeChef","664":"CodeChef","665":"CodeChef","666":"CodeChef","667":"CodeChef","668":"CodeChef","669":"HackerRank-SQL","670":"HackerRank-SQL","671":"HackerRank-C++","672":"CodeWars-Shell","673":"HackerRank-ProblemSolving","674":"HackerRank-C++","675":"HackerRank-C++","676":"CodeChef","677":"CodeChef","678":"CodeChef","679":"CodeChef","680":"CodeChef","681":"CodeChef","682":"CodeChef","683":"CodeChef","684":"CodeChef","685":"CodeChef","686":"CodeChef","687":"CodeChef","688":"CodeChef","689":"CodeChef","690":"CodeChef","691":"CodeChef","692":"CodeChef","693":"CodeChef","694":"CodeChef","695":"CodeChef","696":"CodeChef","697":"CodeChef","698":"CodeChef","699":"CodeChef","700":"CodeChef","701":"CodeChef","702":"HackerRank-ProblemSolving","703":"HackerRank-ProblemSolving","704":"Featured","705":"HackerRank-LinuxShell","706":"HackerRank-LinuxShell","707":"HackerRank-LinuxShell","708":"HackerRank-LinuxShell","709":"HackerRank-C","710":"HackerRank-ProblemSolving","711":"HackerRank-Python","712":"HackerRank-SQL","713":"HackerRank-C","714":"HackerRank-ProblemSolving","715":"HackerRank-C++","716":"HackerRank-C","717":"HackerRank-Python","718":"HackerRank-Python","719":"HackerRank-SQL","720":"HackerRank-Regex","721":"HackerRank-Regex","722":"HackerRank-C","723":"HackerRank-Python","724":"ProjectEuler","725":"HackerRank-C++","726":"CodeWars-Shell","727":"HackerRank-Python","728":"HackerRank-C++","729":"HackerRank-SQL","730":"HackerRank-C","731":"HackerRank-C","732":"HackerRank-Python","733":"HackerRank-Python","734":"HackerRank-Python","735":"CodeChef","736":"CodeChef","737":"HackerRank-ProblemSolving","738":"HackerRank-C","739":"HackerRank-ProblemSolving","740":"CodeChef","741":"CodeChef","742":"CodeChef","743":"CodeChef","744":"CodeChef","745":"CodeChef","746":"CodeChef","747":"CodeChef","748":"CodeChef","749":"CodeChef","750":"CodeChef","751":"CodeChef","752":"CodeChef","753":"CodeChef","754":"CodeChef","755":"CodeChef","756":"CodeChef","757":"HackerRank-Python","758":"HackerRank-Python","759":"HackerRank-Python","760":"HackerRank-LinuxShell","761":"HackerRank-C++","762":"HackerRank-Python","763":"CodeWars-Shell","764":"HackerRank-Python","765":"CodeWars-Shell","766":"CodeWars-Shell","767":"CodeWars-Shell","768":"HackerRank-LinuxShell","769":"HackerRank-ProblemSolving","770":"CodeWars-Shell","771":"CodeWars-Shell","772":"CodeWars-Shell","773":"HackerRank-SQL","774":"HackerRank-SQL","775":"HackerRank-SQL","776":"HackerRank-SQL","777":"HackerRank-SQL","778":"HackerRank-ProblemSolving","779":"CodeChef","780":"CodeChef","781":"CodeChef","782":"CodeChef","783":"CodeChef","784":"CodeChef","785":"CodeChef","786":"CodeChef","787":"CodeChef","788":"CodeChef","789":"CodeChef","790":"CodeChef","791":"CodeChef","792":"CodeChef","793":"CodeChef","794":"CodeChef","795":"CodeChef","796":"HackerRank-SQL","797":"CodeChef","798":"CodeChef","799":"CodeChef","800":"CodeChef","801":"CodeChef","802":"CodeChef","803":"CodeChef","804":"CodeChef","805":"CodeChef","806":"CodeChef","807":"CodeChef","808":"HackerRank-ProblemSolving","809":"HackerRank-C++","810":"HackerRank-Python","811":"HackerRank-Regex","812":"HackerRank-LinuxShell","813":"HackerRank-LinuxShell","814":"HackerRank-LinuxShell","815":"HackerRank-LinuxShell","816":"HackerRank-LinuxShell","817":"HackerRank-SQL","818":"HackerRank-SQL","819":"HackerRank-ProblemSolving","820":"HackerRank-ProblemSolving","821":"HackerRank-ProblemSolving","822":"HackerRank-Python","823":"HackerRank-Python","824":"HackerRank-Python","825":"HackerRank-Python","826":"HackerRank-Python","827":"HackerRank-Python","828":"HackerRank-Python","829":"HackerRank-C++","830":"HackerRank-Python","831":"HackerRank-ProblemSolving","832":"HackerRank-ProblemSolving","833":"HackerRank-ProblemSolving","834":"HackerRank-ProblemSolving","835":"CodeWars-Shell","836":"HackerRank-ProblemSolving","837":"HackerRank-LinuxShell","838":"HackerRank-C","839":"ProjectEuler","840":"HackerRank-ProblemSolving","841":"HackerRank-ProblemSolving","842":"HackerRank-LinuxShell","843":"HackerRank-LinuxShell","844":"HackerRank-LinuxShell","845":"HackerRank-LinuxShell","846":"HackerRank-LinuxShell","847":"HackerRank-LinuxShell","848":"HackerRank-LinuxShell","849":"HackerRank-C","850":"HackerRank-ProblemSolving","851":"ProjectEuler","852":"CodeWars-Shell","853":"HackerRank-Regex","854":"HackerRank-ProblemSolving","855":"HackerRank-Python","856":"HackerRank-ProblemSolving","857":"HackerRank-ProblemSolving","858":"HackerRank-Python","859":"HackerRank-Python","860":"HackerRank-Python","861":"CodeWars-Shell","862":"HackerRank-C++","863":"HackerRank-C++","864":"HackerRank-ProblemSolving","865":"HackerRank-C++","866":"HackerRank-C","867":"HackerRank-C","868":"CodeWars-Shell","869":"HackerRank-C","870":"HackerRank-Python","871":"HackerRank-C","872":"CodeWars-Shell","873":"CodeWars-Shell","874":"ProjectEuler","875":"ProjectEuler","876":"HackerRank-ProblemSolving","877":"Featured","878":"HackerRank-Python","879":"HackerRank-SQL","880":"CodeChef","881":"CodeChef","882":"CodeChef","883":"CodeChef","884":"CodeChef","885":"CodeChef","886":"CodeChef","887":"CodeChef","888":"CodeChef","889":"CodeChef","890":"CodeChef","891":"CodeChef","892":"CodeChef","893":"CodeChef","894":"CodeChef","895":"CodeChef","896":"CodeChef","897":"CodeChef","898":"CodeChef","899":"CodeChef","900":"CodeChef","901":"CodeChef","902":"CodeChef","903":"HackerRank-LinuxShell","904":"HackerRank-LinuxShell","905":"CodeWars-Shell","906":"HackerRank-ProblemSolving","907":"HackerRank-Python","908":"HackerRank-Python","909":"HackerRank-SQL","910":"HackerRank-ProblemSolving","911":"HackerRank-Regex","912":"HackerRank-Python","913":"HackerRank-ProblemSolving","914":"HackerRank-ProblemSolving","915":"HackerRank-ProblemSolving","916":"HackerRank-Python","917":"HackerRank-SQL","918":"HackerRank-ProblemSolving","919":"HackerRank-LinuxShell","920":"CodeWars-Shell","921":"HackerRank-ProblemSolving","922":"HackerRank-Python","923":"HackerRank-SQL","924":"HackerRank-SQL","925":"CodeWars-Shell","926":"HackerRank-ProblemSolving","927":"HackerRank-LinuxShell","928":"HackerRank-LinuxShell","929":"HackerRank-LinuxShell","930":"HackerRank-Python","931":"HackerRank-Python","932":"HackerRank-Python","933":"HackerRank-Python","934":"CodeWars-Shell","935":"HackerRank-ProblemSolving","936":"HackerRank-ProblemSolving","937":"CodeWars-Shell","938":"HackerRank-SQL","939":"CodeChef","940":"HackerRank-Regex","941":"CodeChef","942":"CodeChef","943":"CodeChef","944":"HackerRank-LinuxShell","945":"HackerRank-LinuxShell","946":"HackerRank-LinuxShell","947":"HackerRank-LinuxShell","948":"HackerRank-Regex","949":"HackerRank-ProblemSolving","950":"CodeChef","951":"CodeChef","952":"CodeChef","953":"CodeChef","954":"CodeChef","955":"HackerRank-Regex","956":"HackerRank-Python","957":"HackerRank-Python","958":"HackerRank-Python","959":"HackerRank-Python","960":"HackerRank-Python","961":"HackerRank-Python","962":"HackerRank-Python","963":"HackerRank-C++","964":"HackerRank-C","965":"HackerRank-C++","966":"HackerRank-C++","967":"HackerRank-C++","968":"HackerRank-ProblemSolving","969":"HackerRank-C++","970":"CodeWars-Shell","971":"CodeChef","972":"CodeChef","973":"CodeChef","974":"HackerRank-SQL","975":"HackerRank-SQL","976":"HackerRank-SQL","977":"HackerRank-SQL","978":"HackerRank-SQL","979":"HackerRank-SQL","980":"HackerRank-SQL","981":"HackerRank-SQL","982":"HackerRank-SQL","983":"HackerRank-SQL","984":"HackerRank-SQL","985":"HackerRank-SQL","986":"HackerRank-SQL","987":"HackerRank-SQL","988":"HackerRank-SQL","989":"HackerRank-SQL","990":"HackerRank-SQL","991":"HackerRank-SQL","992":"HackerRank-SQL","993":"HackerRank-SQL","994":"HackerRank-ProblemSolving","995":"CodeWars-Shell","996":"HackerRank-Python","997":"HackerRank-Python","998":"HackerRank-Python","999":"HackerRank-Python","1000":"CodeChef","1001":"HackerRank-Python","1002":"HackerRank-Python","1003":"CodeChef","1004":"CodeChef","1005":"CodeChef","1006":"HackerRank-Python","1007":"HackerRank-Python","1008":"HackerRank-Python","1009":"HackerRank-Python","1010":"HackerRank-Python","1011":"HackerRank-Python","1012":"HackerRank-Python","1013":"HackerRank-Python","1014":"HackerRank-Python"}}